gaanadl/__init__.py
gaanadl/gaana_argparser.py
gaanadl/gaana_cipher.py
gaanadl/skeleton.py
GaanaDL-1.0.0.dist-info/AUTHORS.rst
GaanaDL-1.0.0.dist-info/LICENSE.txt
GaanaDL-1.0.0.dist-info/METADATA
GaanaDL-1.0.0.dist-info/WHEEL
GaanaDL-1.0.0.dist-info/entry_points.txt
GaanaDL-1.0.0.dist-info/top_level.txt
GaanaDL-1.0.0.dist-info/RECORD
