Metadata-Version: 2.1
Name: GaanaDL
Version: 1.0.0
Summary: Gaana Downloader
Home-page: https://github.com/adityastic/gaanadl
Author: Aditya Gupta
Author-email: adityaofficialgupta@gmail.com
License: mit
Project-URL: Documentation, https://github.com/adityastic/gaanadl
Platform: any
Classifier: Development Status :: 5 - Production/Stable
Classifier: Topic :: Utilities
Classifier: Programming Language :: Python
Classifier: Programming Language :: Python :: 3
Classifier: Programming Language :: Python :: 3.4
Classifier: Programming Language :: Python :: 3.5
Classifier: Programming Language :: Python :: 3.6
Classifier: Environment :: Console
Classifier: Intended Audience :: Developers
Classifier: License :: OSI Approved :: MIT License
Classifier: Operating System :: POSIX :: Linux
Classifier: Operating System :: Unix
Classifier: Operating System :: MacOS
Classifier: Operating System :: Microsoft :: Windows
Requires-Dist: requests
Requires-Dist: pycryptodome
Provides-Extra: testing
Requires-Dist: pytest ; extra == 'testing'
Requires-Dist: pytest-cov ; extra == 'testing'
